rascpy/AD.cpython-314-x86_64-linux-gnu.so
rascpy/Bins.cpython-314-x86_64-linux-gnu.so
rascpy/Category.cpython-314-x86_64-linux-gnu.so
rascpy/Config.cpython-314-x86_64-linux-gnu.so
rascpy/Cutter.cpython-314-x86_64-linux-gnu.so
rascpy/DC.cpython-314-x86_64-linux-gnu.so
rascpy/DP.cpython-314-x86_64-linux-gnu.so
rascpy/Datas.py
rascpy/Dats.pkl
rascpy/Filter.py
rascpy/Impute.py
rascpy/Index.py
rascpy/LICENSE.txt
rascpy/Lan_CHN.py
rascpy/Lan_EN.py
rascpy/Performance.py
rascpy/Reg_Step_Wise_MP.cpython-314-x86_64-linux-gnu.so
rascpy/RejInfer.py
rascpy/Report.cpython-314-x86_64-linux-gnu.so
rascpy/SIMS.cpython-314-x86_64-linux-gnu.so
rascpy/Sampling.cpython-314-x86_64-linux-gnu.so
rascpy/ScoreCard.cpython-314-x86_64-linux-gnu.so
rascpy/ScoreCardRej.cpython-314-x86_64-linux-gnu.so
rascpy/Stat.cpython-314-x86_64-linux-gnu.so
rascpy/StepwiseRegressionSKLearn.cpython-314-x86_64-linux-gnu.so
rascpy/Tool.py
rascpy/Tree.cpython-314-x86_64-linux-gnu.so
rascpy/TreeRej.py
rascpy/VAD.cpython-314-x86_64-linux-gnu.so
rascpy/__init__.py
rascpy-2026.1.19.dist-info/METADATA
rascpy-2026.1.19.dist-info/WHEEL
rascpy-2026.1.19.dist-info/top_level.txt
rascpy-2026.1.19.dist-info/RECORD
rascpy-2026.1.19.dist-info/licenses/rascpy/LICENSE.txt
