Metadata-Version: 2.1
Name: rascpy
Version: 2026.1.19
Summary: The rascpy project supplement and improve existing statistical methods such as bidirectional stepwise regression,optimal binning,risk scorecard,automatic parameter search for ensemble trees,filling and transforming complex data with both missing and special values,high-dimensional stratified sampling,reject inference.An major area is credit risk Management.
Author: SIFU DATA SCIENCE
Author-email: scoreconflow@gmail.com
License: Apache-2.0
Project-URL: English Repository, https://github.com/sifuHK/rasc
Project-URL: 中文网址, https://gitee.com/sifuHK/rasc
Keywords: Credit Risk Management,Scorecard,Optimal Bins,Auto Report,XGB Auto Params Search,Step-Wise Liner-Regression,Step-Wise Logistic-Regression,Reject Inference
Classifier: Development Status :: 5 - Production/Stable
Classifier: Programming Language :: Python :: 3.9
Classifier: Programming Language :: Python :: 3.10
Classifier: Programming Language :: Python :: 3.11
Classifier: Programming Language :: Python :: 3.12
Classifier: Programming Language :: Python :: 3.13
Classifier: Programming Language :: Python :: 3.14
Classifier: Programming Language :: C
License-File: rascpy/LICENSE.txt
Requires-Dist: psutil>=5.9.1
Requires-Dist: pandas>=1.2.4
Requires-Dist: scikit-learn>=0.24.2
Requires-Dist: statsmodels>=0.12.2
Requires-Dist: openpyxl>=3.0.4
Requires-Dist: cryptography>=38.0.4
Requires-Dist: matplotlib>=3.2.1
Requires-Dist: ntplib>=0.4.0
Requires-Dist: seaborn>=0.11.0
Requires-Dist: flaml[automl]>=2.1.2
Requires-Dist: cffi>=1.14.4
Requires-Dist: jinja2>=2.11.2
Requires-Dist: pillow>=11.2.0
